Workbook

Sheet ESF
A1: Cuenta | B1: 2012 | C1: 2013 | D1: 2014 | E1: 2015 | F1: 2016 | G1: 2017 | H1: 2018 | I1: 2019 | J1: 2020 | K1: 2021 | L1: 2022 | M1: 2023 | N1: PROMEDIO
A2: Efectivo y Equivalentes al Efectivo | B2: 24270 | C2: 72220 | D2: 147763 | E2: 117685 | F2: 54338 | G2: 227520 | H2: 560344 | I2: 579929 | J2: 477083 | K2: 234978 | L2: 57583 | M2: 69594 | N2: 218608.92
A3: Cuentas por Cobrar Comerciales y Otras Cuentas por Cobrar | B3: 361711 | C3: 384189 | D3: 300716 | E3: 305848 | F3: 251372 | G3: 371175 | H3: 332529 | I3: 334511 | J3: 214400 | K3: 354730 | L3: 446390 | M3: 467826 | N3: 343783.08
A4: Cuentas por Cobrar Comerciales | B4: 202435 | C4: 239998 | D4: 253730 | E4: 242078 | F4: 192422 | G4: 201889 | H4: 224375 | I4: 249656 | J4: 206853 | K4: 320685 | L4: 394126 | M4: 387036 | N4: 259606.92
A5: Cuentas por Cobrar a Entidades Relacionadas | B5: 158435 | C5: 144191 | D5: 46834 | E5: 0 | F5: 204 | G5: 0 | H5: 0 | I5: 0 | J5: 0 | K5: 0 | L5: 0 | M5: 34 | N5: 29141.5
A6: Otras Cuentas por Cobrar | B6: 841 | C6: 0 | D6: 152 | E6: 63770 | F6: 58746 | G6: 169286 | H6: 108154 | I6: 84855 | J6: 7547 | K6: 34045 | L6: 52264 | M6: 80756 | N6: 55034.667
A7: Inventarios | B7: 625167 | C7: 604797 | D7: 431449 | E7: 383387 | F7: 377821 | G7: 417819 | H7: 405120 | I7: 419048 | J7: 315056 | K7: 966521 | L7: 1184636 | M7: 692069 | N7: 568574.17
A8: Activos Corrientes Distintos al Efectivo Pignorados como Garantía Colateral | B8: 1011148 | C8: 1061206 | D8: 879928 | E8: 0 | F8: 0 | G8: 0 | H8: 0 | I8: 0 | J8: 0 | K8: 0 | L8: 0 | M8: 0 | N8: 246023.5
A9: Total Activos Corrientes Distintos de los Activos no Corrientes | B9: 0 | C9: 0 | D9: 0 | E9: 806920 | F9: 683531 | G9: 1016514 | H9: 1297993 | I9: 1333488 | J9: 1006539 | K9: 1556229 | L9: 1688609 | M9: 1229489 | N9: 884942.67
A10: Total Activos Corrientes | B10: 1011148 | C10: 1061206 | D10: 879928 | E10: 806920 | F10: 683531 | G10: 1016514 | H10: 1297993 | I10: 1333488 | J10: 1006539 | K10: 1556229 | L10: 1688609 | M10: 1229489 | N10: 1130966.2
A11: Otros Activos Financieros | B11: 0 | C11: 0 | D11: 0 | E11: 0 | F11: 0 | G11: 0 | H11: 0 | I11: 0 | J11: 0 | K11: 0 | L11: 0 | M11: 0 | N11: 0
A12: Inversiones en Subsidiarias, Negocios Conjuntos y Asociadas | B12: 0 | C12: 0 | D12: 0 | E12: 0 | F12: 0 | G12: 0 | H12: 0 | I12: 0 | J12: 0 | K12: 0 | L12: 0 | M12: 0 | N12: 0
A13: Cuentas por Cobrar Comerciales y Otras Cuentas por Cobrar | B13: 0 | C13: 0 | D13: 62113 | E13: 53097 | F13: 52190 | G13: 23596 | H13: 912 | I13: 912 | J13: 74131 | K13: 74131 | L13: 74131 | M13: 912 | N13: 34677.083
... A42: TOTAL PASIVO Y PATRIMONIO | B42: 2049691 | C42: 2060980 | D42: 1693563 | E42: 1579306 | F42: 1383923 | G42: 1604011 | H42: 1827516 | I42: 1826779 | J42: 1534056 | K42: 2073337 | L42: 2213951 | M42: 1705899 | N42: 1796084.3

Sheet EERR
A1: Cuenta | B1: 2012 | C1: 2013 | D1: 2014 | E1: 2015 | F1: 2016 | G1: 2017 | H1: 2018 | I1: 2019 | J1: 2020 | K1: 2021 | L1: 2022 | M1: 2023 | N1: Promedio EERR
A2: Ingresos de Actividades Ordinarias | B2: 1681492 | C2: 1738496 | D2: 1607544 | E2: 1486080 | F2: 1437931 | G2: 1323554 | H2: 1580684 | I2: 1578074 | J2: 1368465 | K2: 2439612 | L2: 2743235 | M2: 2384796 | N2: =+AVERAGE(B2:M2) -> 1780830.2
A3: Costo de Ventas | B3: -1716145 | C3: -1616987 | D3: -1614156 | E3: -1369975 | F3: -1268306 | G3: -1168985 | H3: -1354496 | I3: -1415806 | J3: -1152699 | K3: -1897278 | L3: -2359981 | M3: -2157883 | N3: =+AVERAGE(B3:M3) -> -1591058.1
A4: Ganancia (Pérdida) Bruta | B4: -34653 | C4: 121509 | D4: -6612 | E4: 116105 | F4: 169625 | G4: 154569 | H4: 226188 | I4: 162268 | J4: 215766 | K4: 542334 | L4: 383254 | M4: 226913 | N4: =+AVERAGE(B4:M4) -> 189772.17
A5: Gastos de Ventas y Distribución | B5: -51640 | C5: -13835 | D5: -20918 | E5: -20538 | F5: -19077 | G5: -16549 | H5: -17290 | I5: -19672 | J5: -16188 | K5: -23336 | L5: -23185 | M5: -20748 | N5: =+AVERAGE(B5:M5) -> -21914.667
A6: Gastos de Administración | B6: -45229 | C6: -41472 | D6: -44624 | E6: -41046 | F6: -33951 | G6: -38137 | H6: -31074 | I6: -31537 | J6: -28229 | K6: -36068 | L6: -41755 | M6: -42313 | N6: =+AVERAGE(B6:M6) -> -37952.917
A7: Otros Ingresos Operativos | B7: 8537 | C7: 13032 | D7: 25443 | E7: 9459 | F7: 20949 | G7: 125644 | H7: 10338 | I7: 25159 | J7: 22207 | K7: 22498 | L7: 10890 | M7: 28870 | N7: =+AVERAGE(B7:M7) -> 26918.833
A8: Otros Gastos Operativos | B8: -26608 | C8: -11705 | D8: -224227 | E8: -6617 | F8: -8697 | G8: -45353 | H8: -8423 | I8: -2619 | J8: -17068 | K8: -7698 | L8: -3370 | M8: -11213 | N8: =+AVERAGE(B8:M8) -> -31133.167
A9: Ganancia (Pérdida) Operativa | B9: -149593 | C9: 67529 | D9: -270938 | E9: 57363 | F9: 128849 | G9: 180174 | H9: 179739 | I9: 133599 | J9: 176488 | K9: 497730 | L9: 325834 | M9: 181509 | N9: =+AVERAGE(B9:M9) -> 125690.25
A10: Ingresos Financieros | B10: 1114 | C10: 1370 | D10: 1140 | E10: 1615 | F10: 1282 | G10: 2529 | H10: 7468 | I10: 12845 | J10: 5191 | K10: 1385 | L10: 2227 | M10: 29300 | N10: =+AVERAGE(B10:M10) -> 5622.1667
A11: Gastos Financieros | B11: -29596 | C11: -19201 | D11: -12957 | E11: -11445 | F11: -7211 | G11: -2366 | H11: -4 | I11: -671 | J11: -2870 | K11: -798 | L11: -8339 | M11: -35958 | N11: =+AVERAGE(B11:M11) -> -10951.333
A12: Diferencias de Cambio Neto | B12: 45894 | C12: -47558 | D12: -20310 | E12: -31012 | F12: -1794 | G12: -4937 | H12: 4668 | I12: -8653 | J12: 12029 | K12: -37004 | L12: 995 | M12: 6705 | N12: =+AVERAGE(B12:M12) -> -6748.0833
A13: Ganancia (Pérdida) antes de Impuestos | B13: -132181 | C13: 2140 | D13: -303065 | E13: 16521 | F13: 121126 | G13: 175400 | H13: 191871 | I13: 137120 | J13: 190838 | K13: 461313 | L13: 320717 | M13: 181556 | N13: =+AVERAGE(B13:M13) -> 113613
... A20: Total de Ganancias (Pérdida) Diluida por Acción Ordinaria | B20: -0.108 | C20: -0.002 | D20: -0.167 | E20: 0.012 | F20: 0.082 | G20: 0.115 | H20: 0.108 | I20: 0.073 | J20: 0.125 | K20: 0.461 | L20: 0.315 | M20: 0.165 | N20: =+AVERAGE(B20:M20) -> 0.09825

Sheet Flowcash
A1: Cuenta | B1: 2012 | C1: 2013 | D1: 2014 | E1: 2015 | F1: 2016 | G1: 2017 | H1: 2018 | I1: 2019 | J1: 2020 | K1: 2021 | L1: 2022 | M1: 2023 | N1: PROMEDIO
A2: Flujo de Efectivo de Actividades de Operación | B2: 0 | C2: 0 | D2: 0 | E2: 0 | F2: 0 | G2: 0 | H2: 0 | I2: 0 | J2: 0 | K2: 0 | L2: 0 | M2: 0 | N2: =+AVERAGE(B2:M2) -> 0
A3: Clases de Cobros en Efectivo por Actividades de Operación | B3: 0 | C3: 0 | D3: 0 | E3: 0 | F3: 0 | G3: 0 | H3: 0 | I3: 0 | J3: 0 | K3: 0 | L3: 0 | M3: 0 | N3: =+AVERAGE(B3:M3) -> 0
A4: Venta de Bienes y Prestación de Servicios | B4: 1651044 | C4: 1701344 | D4: 1597781 | E4: 1495724 | F4: 1496808 | G4: 1314534 | H4: 1557291 | I4: 1552782 | J4: 1408995 | K4: 2323516 | L4: 2670385 | M4: 2392200 | N4: =+AVERAGE(B4:M4) -> 1763533.7
A5: Regalías, Cuotas, Comisiones, Otros Ingresos de Actividades Ordinarias | B5: 0 | C5: 0 | D5: 0 | E5: 0 | F5: 0 | G5: 0 | H5: 0 | I5: 0 | J5: 0 | K5: 0 | L5: 0 | M5: 0 | N5: =+AVERAGE(B5:M5) -> 0
A6: Contratos Mantenidos con Propósito de Intermediación o para Negociar | B6: 0 | C6: 0 | D6: 0 | E6: 0 | F6: 0 | G6: 0 | H6: 0 | I6: 0 | J6: 0 | K6: 0 | L6: 0 | M6: 0 | N6: =+AVERAGE(B6:M6) -> 0
A7: Arrendamiento y Posterior Venta de Activos Mantenidos para Arrendar a Terceros | B7: 0 | C7: 0 | D7: 0 | E7: 0 | F7: 0 | G7: 0 | H7: 0 | I7: 0 | J7: 0 | K7: 0 | L7: 0 | M7: 0 | N7: =+AVERAGE(B7:M7) -> 0
A8: Otros Cobros de Efectivo Relativos a las Actividades de Operación | B8: 0 | C8: 0 | D8: 0 | E8: 0 | F8: 0 | G8: 0 | H8: 0 | I8: 0 | J8: 0 | K8: 0 | L8: 0 | M8: 233997 | N8: =+AVERAGE(B8:M8) -> 19499.75
A9: Clases de Pagos en Efectivo por Actividades de Operación | B9: 0 | C9: 0 | D9: 0 | E9: 0 | F9: 0 | G9: 0 | H9: 0 | I9: 0 | J9: 0 | K9: 0 | L9: 0 | M9: 0 | N9: =+AVERAGE(B9:M9) -> 0
A10: Proveedores de Bienes y Servicios | B10: -1527327 | C10: -1389848 | D10: -1330604 | E10: -1284329 | F10: -1115132 | G10: -971789 | H10: -1068502 | I10: -1193496 | J10: -860033 | K10: -1360437 | L10: -2142246 | M10: -2177062 | N10: =+AVERAGE(B10:M10) -> -1368400.4
A11: Contratos Mantenidos con Propósito de Intermediación o para Negociar | B11: 0 | C11: 0 | D11: 0 | E11: 0 | F11: 0 | G11: 0 | H11: 0 | I11: 0 | J11: 0 | K11: 0 | L11: 0 | M11: 0 | N11: =+AVERAGE(B11:M11) -> 0
A12: Pagos a y por Cuenta de los Empleados | B12: -82309 | C12: -70625 | D12: -70438 | E12: -77807 | F12: -69302 | G12: -123698 | H12: -131589 | I12: -135633 | J12: -121118 | K12: -176834 | L12: -163151 | M12: -161793 | N12: =+AVERAGE(B12:M12) -> -115358.08
A13: Elaboración o Adquisición de Activos para Arrendar y Otros Mantenidos para la Venta | B13: 0 | C13: 0 | D13: 0 | E13: 0 | F13: 0 | G13: 0 | H13: 0 | I13: 0 | J13: 0 | K13: 0 | L13: 0 | M13: 0 | N13: =+AVERAGE(B13:M13) -> 0
... A75: Efectivo y Equivalente al Efectivo al Finalizar el Ejercicio | B75: 24270 | C75: 72220 | D75: 147763 | E75: 117685 | F75: 54338 | G75: 227520 | H75: 560344 | I75: 579929 | J75: 477083 | K75: 234978 | L75: 57583 | M75: 69594 | N75: =+AVERAGE(B75:M75) -> 218608.92

Sheet Planeamiento Financiero
C2: Planeamiento Financiero de la empresa Siderperu S.A.A.
C3: 1) Proyección de las principales cuentas del Estado de Situación Financiera
C4: Se realiza una proyección utilizando la proyección del crecimiento de las principales cuentas del ESF.
C6: Cuenta | D6: Ingresos de Actividades Ordinarias | E6: Efectivo y Equivalentes al Efectivo | F6: Cuentas por cobrar totales | G6: Inventarios | H6: Cuentas por pagar totales
C7: 2012 | D7: 1681492 | E7: 24270 | F7: 0 | G7: 625167 | H7: 202058
C8: 2013 | D8: 1738496 | E8: 72220 | F8: 0 | G8: 604797 | H8: 421256
C9: 2014 | D9: 1607544 | E9: 147763 | F9: 124226 | G9: 431449 | H9: 349508
C10: 2015 | D10: 1486080 | E10: 117685 | F10: 106194 | G10: 383387 | H10: 270100
C11: 2016 | D11: 1437931 | E11: 54338 | F11: 104380 | G11: 377821 | H11: 412236
C12: 2017 | D12: 1323554 | E12: 227520 | F12: 47192 | G12: 417819 | H12: 570290
C13: 2018 | D13: 1580684 | E13: 560344 | F13: 1824 | G13: 405120 | H13: 727030
C14: 2019 | D14: 1578074 | E14: 579929 | F14: 1824 | G14: 419048 | H14: 776808
C15: 2020 | D15: 1368465 | E15: 477083 | F15: 148262 | G15: 315056 | H15: 817476
C16: 2021 | D16: 2439612 | E16: 234978 | F16: 148262 | G16: 966521 | H16: 1943568
C17: 2022 | D17: 2743235 | E17: 57583 | F17: 148262 | G17: 1184636 | H17: 1983684
C18: 2023 | D18: 2384796 | E18: 69594 | F18: 1824 | G18: 692069 | H18: 1008688
C19: Proy 2024 | D19: 2500000 | E19: =+E37*$D$19 -> 106478.74 | F19: =+F18 -> 1824 | G19: =+G37*$D$19 -> 949528.22 | H19: 600000
C21: 2) Proyección del crecimiento de las principales cuentas del Estado de Situación Financiera
C22: La proyección del crecimiento se realiza a partir de la participación de las cuentas (variables) respecto al nivel de ventas.
C24: Cuenta | D24: Ingresos de Actividades Ordinarias | E24: Efectivo y Equivalentes al Efectivo | F24: Cuentas por cobrar totales | G24: Inventarios | H24: Cuentas por pagar totales
C25: 2012 | D25: 1681492 | E25: =+E7/$D7 -> 0.01443361 | F25: =+F7/$D7 -> 0 | G25: =+G7/$D7 -> 0.37179303 | H25: =+H7/$D7 -> 0.1201659
C26: 2013 | D26: 1738496 | E26: =+E8/$D8 -> 0.041541654 | F26: =+F8/$D8 -> 0 | G26: =+G8/$D8 -> 0.34788518 | H26: =+H8/$D8 -> 0.24231059
C27: 2014 | D27: 1607544 | E27: =+E9/$D9 -> 0.091918479 | F27: =+F9/$D9 -> 0.077276889 | G27: =+G9/$D9 -> 0.26839017 | H27: =+H9/$D9 -> 0.21741738
C28: 2015 | D28: 1486080 | E28: =+E10/$D10 -> 0.079191564 | F28: =+F10/$D10 -> 0.071459141 | G28: =+G10/$D10 -> 0.25798544 | H28: =+H10/$D10 -> 0.18175334
C29: 2016 | D29: 1437931 | E29: =+E11/$D11 -> 0.037789018 | F29: =+F11/$D11 -> 0.072590409 | G29: =+G11/$D11 -> 0.26275322 | H29: =+H11/$D11 -> 0.28668691
C30: 2017 | D30: 1323554 | E30: =+E12/$D12 -> 0.17190081 | F30: =+F12/$D12 -> 0.035655515 | G30: =+G12/$D12 -> 0.3156796 | H30: =+H12/$D12 -> 0.43087777
C31: 2018 | D31: 1580684 | E31: =+E13/$D13 -> 0.35449464 | F31: =+F13/$D13 -> 0.0011539308 | G31: =+G13/$D13 -> 0.25629411 | H31: =+H13/$D13 -> 0.45994645
C32: 2019 | D32: 1578074 | E32: =+E14/$D14 -> 0.36749164 | F32: =+F14/$D14 -> 0.0011558393 | G32: =+G14/$D14 -> 0.26554395 | H32: =+H14/$D14 -> 0.49225068
C33: 2020 | D33: 1368465 | E33: =+E15/$D15 -> 0.34862638 | F33: =+F15/$D15 -> 0.10834183 | G33: =+G15/$D15 -> 0.23022584 | H33: =+H15/$D15 -> 0.59736712
C34: 2021 | D34: 2439612 | E34: =+E16/$D16 -> 0.096317775 | F34: =+F16/$D16 -> 0.060772779 | G34: =+G16/$D16 -> 0.39617816 | H34: =+H16/$D16 -> 0.79667095
C35: 2022 | D35: 2743235 | E35: =+E17/$D17 -> 0.02099091 | F35: =+F17/$D17 -> 0.054046409 | G35: =+G17/$D17 -> 0.43183905 | H35: =+H17/$D17 -> 0.72311851
C36: 2023 | D36: 2384796 | E36: =+E18/$D18 -> 0.02918237 | F36: =+F18/$D18 -> 0.00076484529 | G36: =+G18/$D18 -> 0.2902005 | H36: =+H18/$D18 -> 0.42296616
C37: Proy 2024 | D37: 2500000 | E37: =+_xlfn.FORECAST.LINEAR($D$37,E25:E36,$D$25:$D$36) -> 0.042591497 | F37: =+F19/D19 -> 0.0007296 | G37: =+_xlfn.FORECAST.LINEAR($D$37,G25:G36,$D$25:$D$36) -> 0.37981129 | H37: =+H19/D19 -> 0.24
C38: Nota: Este análisis se realiza a partir de los datos históricos presentado en los Estados Financieros 2012-2013
C39: La empresa mantiene una política de reducción de Cuents por Cobrar y Cuentas por Pagar, tras la pandemia COVID.19. Se asume un valor promedio previo a la pandemia de 0% y 24%, respectivamente.
B41: 3) Estado de Situación Financiera proyectado y comparado con el año 2023
B42: A partir de la información presentada, se realiza el ESF proyectado utilizando las variables (cuentas) modificadas.
B44: Cuenta | C44: 2023 | D44: Proy 2024
B45: Efectivo y Equivalentes al Efectivo | C45: 69594 | D45: =+$E$19 -> 106478.74
B46: Cuentas por cobrar totales | C46: 1824 | D46: =+$F$19 -> 1824
B47: Inventarios | C47: 692069 | D47: =+$G$19 -> 949528.22
B48: Activos Corrientes Distintos al Efectivo Pignorados como Garantía Colateral | C48: 0 | D48: =+C48 -> 0
B49: Total Activos Corrientes Distintos de los Activos no Corrientes | C49: 1229489 | D49: =+C49 -> 1229489
B50: Total Activos Corrientes | C50: 1229489 | D50: =+SUM(D45:D49) -> 2287320
B51: Otros Activos Financieros | C51: 0 | D51: =+C51 -> 0
B52: Inversiones en Subsidiarias, Negocios Conjuntos y Asociadas | C52: 0 | D52: =+C52 -> 0
B53: Cuentas por Cobrar Comerciales y Otras Cuentas por Cobrar | C53: 912 | D53: =+C53 -> 912
B54: Cuentas por Cobrar Comerciales | C54: 0 | D54: =+C54 -> 0
B55: Cuentas por Cobrar a Entidades Relacionadas | C55: 0 | D55: =+C55 -> 0
B56: Otras Cuentas por Cobrar | C56: 912 | D56: =+C56 -> 912
B57: Propiedades de Inversión | C57: 0 | D57: =+C57 -> 0
B58: Propiedades, Planta y Equipo | C58: 473182 | D58: =+C58 -> 473182
B59: Activos Intangibles Distintos de la Plusvalía | C59: 2316 | D59: =+C59 -> 2316
B60: Activos por Impuestos Diferidos | C60: 0 | D60: =+C60 -> 0
B61: Total Activos No Corrientes | C61: 476410 | D61: =+SUM(D51:D60) -> 477322
B62: TOTAL DE ACTIVOS | C62: 1705899 | D62: =+D50+D61 -> 2764642
B63: Otros Pasivos Financieros | C63: 161420 | D63: =+C63 -> 161420
B64: Cuentas por pagar totales | C64: 1008688 | D64: =+$H$19 -> 600000
B65: Otros Pasivos no Financieros | C65: 4170 | D65: =+C65 -> 4170
B66: Total de Pasivos Corrientes Distintos de Pasivos Incluidos en Grupos de Activos para su Disposición Clasificados como Mantenidos para la Venta | C66: 669934 | D66: =+C66 -> 669934
B67: Total Pasivos Corrientes | C67: 669934 | D67: =+SUM(D63:D66) -> 1728677
B68: Otros Pasivos Financieros | C68: 0 | D68: =+C68 -> 0
B69: Pasivos por Impuestos Diferidos | C69: 3686 | D69: =+C69 -> 3686
B70: Otros Pasivos no Financieros | C70: 7744 | D70: =+C70 -> 7744
B71: Total Pasivos No Corrientes | C71: 11430 | D71: =+SUM(D68:D70) -> 11430
B72: TOTAL PASIVOS | C72: 681364 | D72: =+D67+D71 -> 1740107
B73: Capital Emitido | C73: 700000 | D73: =+C73 -> 700000
B74: Primas de Emisión | C74: 83000 | D74: =+C74 -> 83000
B75: Otras Reservas de Capital | C75: 89234 | D75: =+C75 -> 89234
B76: Resultados Acumulados | C76: 152301 | D76: =+C76 -> 152301
B77: Otras Reservas de Patrimonio | C77: 0 | D77: =+C77 -> 0
B78: TOTAL PATRIMONIO | C78: 1024535 | D78: =+SUM(D73:D77) -> 1024535
B79: TOTAL PASIVO Y PATRIMONIO | C79: 1705899 | D79: =+D72+D78 -> 2764642
B80: Nota: La proyección se realiza con las variaciones presentadas en en cuadro anterior, ceteris paribus.

Sheet Balance Proforma
B1: Balance Pro Forma
B2: 1) Necesidad Operativa de Fondos
B3: Se elabora la estructura resumida del Estado de Situación Financiera proyectado y se contabilizar el NOF.
B5: Activos | C5: Valores | E5: Pasivo y Patrimonio | F5: Valores
B6: Efectivo y Equivalentes al Efectivo | C6: 106478.74 | E6: Cuentas por pagar totales | F6: 600000
B7: Cuentas por cobrar totales | C7: 1824 | E7: TOTAL PASIVOS | F7: 1446954
B8: Inventarios | C8: 949528.22 | E8: Capital Emitido | F8: 700000
B9: ACTIVO CORRIENTE | C9: 2287320 | E9: Otras Reservas de Capital | F9: 89234
B10: Otros Activos Financieros | C10: 0 | E10: Resultados Acumulados | F10: 152301
B11: Propiedades, Planta y Equipo | C11: 473182 | E11: TOTAL PATRIMONIO | F11: 1024535
B12: ACTIVO NO CORRIENTE | C12: 477322 | E12: Necesidad Futura de Fondos | F12: =+C13-2471489 -> 293152.96
B13: TOTAL DE ACTIVOS | C13: =+C9+C12 -> 2764642 | E13: TOTAL PASIVO Y PATRIMONIO | F13: =+F7+F11+F12 -> 2764642
B14: Nota. Esta información es constituida a partir de la información de Planeamiento Financiero.
B16: 2) Balance Contable proyectado
B18: Cuenta | C18: Proy 2024 | E18: Cuenta | F18: Proy 2024
B19: =+'Planeamiento Financiero'!B45 -> Efectivo y Equivalentes al Efectivo | C19: =+'Planeamiento Financiero'!D45 -> 106478.74 | E19: =+'Planeamiento Financiero'!B63 -> Otros Pasivos Financieros | F19: =+'Planeamiento Financiero'!D63 -> 161420
B20: =+'Planeamiento Financiero'!B46 -> Cuentas por cobrar totales | C20: =+'Planeamiento Financiero'!D46 -> 1824 | E20: Cuentas por pagar comerciales | F20: 34677.083
B21: =+'Planeamiento Financiero'!B47 -> Inventarios | C21: =+'Planeamiento Financiero'!D47 -> 949528.22 | E21: Cuentass por pagar a instituciones relacionadas | F21: =+'Planeamiento Financiero'!D64-F20 -> 858475.88
B22: =+'Planeamiento Financiero'!B48 -> Activos Corrientes Distintos al Efectivo Pignorados como Garantía Colateral | C22: =+'Planeamiento Financiero'!D48 -> 0 | E22: =+'Planeamiento Financiero'!B65 -> Otros Pasivos no Financieros | F22: =+'Planeamiento Financiero'!D65 -> 4170
B23: =+'Planeamiento Financiero'!B49 -> Total Activos Corrientes Distintos de los Activos no Corrientes | C23: =+'Planeamiento Financiero'!D49 -> 1229489 | E23: =+'Planeamiento Financiero'!B66 -> Total de Pasivos Corrientes Distintos de Pasivos Incluidos en Grupos de Activos para su Disposición Clasificados como Mantenidos para la Venta | F23: =+'Planeamiento Financiero'!D66 -> 669934
B24: TOTAL ACTIVOS CORRIENTES | C24: =+'Planeamiento Financiero'!D50 -> 2287320 | E24: TOTAL PASIVO CORRIENTE | F24: =+'Planeamiento Financiero'!D67 -> 1728677
B25: =+'Planeamiento Financiero'!B51 -> Otros Activos Financieros | C25: =+'Planeamiento Financiero'!D51 -> 0 | E25: =+'Planeamiento Financiero'!B68 -> Otros Pasivos Financieros | F25: =+'Planeamiento Financiero'!D68 -> 0
B26: =+'Planeamiento Financiero'!B52 -> Inversiones en Subsidiarias, Negocios Conjuntos y Asociadas | C26: =+'Planeamiento Financiero'!D52 -> 0 | E26: =+'Planeamiento Financiero'!B69 -> Pasivos por Impuestos Diferidos | F26: =+'Planeamiento Financiero'!D69 -> 3686
B27: =+'Planeamiento Financiero'!B53 -> Cuentas por Cobrar Comerciales y Otras Cuentas por Cobrar | C27: =+'Planeamiento Financiero'!D53 -> 912 | E27: =+'Planeamiento Financiero'!B70 -> Otros Pasivos no Financieros | F27: =+'Planeamiento Financiero'!D70 -> 7744
B28: =+'Planeamiento Financiero'!B54 -> Cuentas por Cobrar Comerciales | C28: =+'Planeamiento Financiero'!D54 -> 0 | E28: TOTAL PASIVO NO CORRIENTE | F28: =+'Planeamiento Financiero'!D71 -> 11430
B29: =+'Planeamiento Financiero'!B55 -> Cuentas por Cobrar a Entidades Relacionadas | C29: =+'Planeamiento Financiero'!D55 -> 0 | E29: =+'Planeamiento Financiero'!B72 -> TOTAL PASIVOS | F29: =+'Planeamiento Financiero'!D72 -> 1740107
B30: =+'Planeamiento Financiero'!B56 -> Otras Cuentas por Cobrar | C30: =+'Planeamiento Financiero'!D56 -> 912 | E30: =+'Planeamiento Financiero'!B73 -> Capital Emitido | F30: =+'Planeamiento Financiero'!D73 -> 700000
B31: =+'Planeamiento Financiero'!B57 -> Propiedades de Inversión | C31: =+'Planeamiento Financiero'!D57 -> 0 | E31: =+'Planeamiento Financiero'!B74 -> Primas de Emisión | F31: =+'Planeamiento Financiero'!D74 -> 83000
B32: =+'Planeamiento Financiero'!B58 -> Propiedades, Planta y Equipo | C32: =+'Planeamiento Financiero'!D58 -> 473182 | E32: =+'Planeamiento Financiero'!B75 -> Otras Reservas de Capital | F32: =+'Planeamiento Financiero'!D75 -> 89234
B33: =+'Planeamiento Financiero'!B59 -> Activos Intangibles Distintos de la Plusvalía | C33: =+'Planeamiento Financiero'!D59 -> 2316 | E33: =+'Planeamiento Financiero'!B76 -> Resultados Acumulados | F33: =+'Planeamiento Financiero'!D76 -> 152301
B34: =+'Planeamiento Financiero'!B60 -> Activos por Impuestos Diferidos | C34: =+'Planeamiento Financiero'!D60 -> 0 | E34: =+'Planeamiento Financiero'!B77 -> Otras Reservas de Patrimonio | F34: =+'Planeamiento Financiero'!D77 -> 0
B35: TOTAL ACTIVOS NO CORRIENTES | C35: =+'Planeamiento Financiero'!D61 -> 477322 | E35: =+'Planeamiento Financiero'!B78 -> TOTAL PATRIMONIO | F35: =+'Planeamiento Financiero'!D78 -> 1024535
B36: =+'Planeamiento Financiero'!B62 -> TOTAL DE ACTIVOS | C36: =+'Planeamiento Financiero'!D62 -> 2764642 | E36: =+'Planeamiento Financiero'!B79 -> TOTAL PASIVO Y PATRIMONIO | F36: =+'Planeamiento Financiero'!D79 -> 2764642
B37: Nota: se elabora a partir de la proyección de las cuentas del Estado de Situación Financiera
B39: 3) Balance Financiero proyectado
B40: Se elabora a partir del Balance Contable y se determina la estructura óptima del capital con la participación del NOF.
B41: Cuenta | C41: Proy 2024 | E41: Cuenta | F41: Proy 2024
B42: Otros activos corrientes | C42: =+C22+C23 -> 1229489 | E42: Otros pasivos corrientes | F42: =+F19+F22+F23 -> 835524
B44: Efectivo y Equivalentes al Efectivo | C44: =+C19 -> 106478.74 | E44: Proveedores | F44: =+F20 -> 34677.083
E46: Deuda Financiera de Corto Plazo | F46: =+F21-293152.958682308 -> 565322.92
B47: Cuentas por cobrar totales | C47: =+C20 -> 1824
E49: Necesidades Futuras de Fondo | F49: 293152.96
B50: Inventarios | C50: =+C21 -> 949528.22 | E50: Deuda Financiera de Largo plazo | F50: 0
E52: Otro pasivo no corriente | F52: =+F27+F26+F25 -> 11430
B53: Activo Fijo Neto | C53: =+C32 -> 473182 | E53: Patrimonio | F53: =+F35 -> 1024535
B56: Otros activos No Corrientes | C56: =+SUM(C25:C34)-C32 -> 4140
B58: TOTAL ACTIVOS | C58: =+SUM(C42:C57) -> 2764642 | E58: TOTAL PASIVO Y PATRIMONIO | F58: =+SUM(F42:F57) -> 2764642
B59: Nota: el balance financiero se determina y se encuentra la estructura optima de los pasivos corrientes y no corrientes
B60: Las Necesidad Futuras de Fondos se financian en deuda de corto plazo y se registra en Pasivos Corrientes

Sheet Proyección con históricos
B1: Proyección de Ventas
B3: Ventas 2023 | C3: 2384795
B4: Cuadro de Venta histórico 2023
B5: Trimestre | C5: 1T | D5: 2T | E5: 3T | F5: 4T | G5: TOTAL ANUAL
B6: Ingreso | C6: 535833.96 | D6: 541550.72 | E6: 512787.84 | F6: 794622.47 | G6: =+SUM(C6:F6) -> 2384795
B7: Participación total | C7: =+C6/$G$6 -> 0.22468764 | D7: =+D6/$G$6 -> 0.22708481 | E7: =+E6/$G$6 -> 0.21502387 | F7: =+F6/$G$6 -> 0.33320368 | G7: =+SUM(C7:F7) -> 1
B9: Trimestre | C9: 1T | D9: 2T | E9: 3T | F9: 4T | G9: TOTAL ANUAL
B10: Sector de mercado
B11: Construcción Civil | C11: =+C21*$C$3 -> 466740.82 | D11: =+D21*$C$3 -> 467691.87 | E11: =+E21*$C$3 -> 444812.67 | F11: =+F21*$C$3 -> 709256.21 | G11: =+SUM(C11:F11) -> 2088501.6
B12: Industria | C12: =+C22*$C$3 -> 57492.717 | D12: =+D22*$C$3 -> 60390.216 | E12: =+E22*$C$3 -> 55813.158 | F12: =+F22*$C$3 -> 65320.225 | G12: =+SUM(C12:F12) -> 239016.32
B13: Minería | C13: =+C23*$C$3 -> 11600.43 | D13: =+D23*$C$3 -> 13468.634 | E13: =+E23*$C$3 -> 12162.021 | F13: =+F23*$C$3 -> 20046.036 | G13: =+SUM(C13:F13) -> 57277.121
B14: Total | C14: =+C11+C12+C13 -> 535833.96 | D14: =+D11+D12+D13 -> 541550.72 | E14: =+E11+E12+E13 -> 512787.84 | F14: =+F11+F12+F13 -> 794622.47 | G14: =+SUM(G11:G13) -> 2384795
B15: Mercado territorial
B16: Mercado Local | C16: =+C25*$C$3 -> 530931.77 | D16: =+D25*$C$3 -> 534533.43 | E16: =+E25*$C$3 -> 504716.05 | F16: =+F25*$C$3 -> 738268.59 | G16: =+SUM(C16:F16) -> 2308449.8
B17: Mercado Externo | C17: =+C26*$C$3 -> 4902.1899 | D17: =+D26*$C$3 -> 7017.2862 | E17: =+E26*$C$3 -> 8071.7917 | F17: =+F26*$C$3 -> 56353.885 | G17: =+SUM(C17:F17) -> 76345.153
B18: Total | C18: =+C16+C17 -> 535833.96 | D18: =+D16+D17 -> 541550.72 | E18: =+E16+E17 -> 512787.84 | F18: =+F16+F17 -> 794622.47 | G18: =+G16+G17 -> 2384795
B19: Participación parcial
B20: Sector de mercado
B21: Construcción Civil | C21: =1-D21-E21-F21-C22-D22-E22-F22-C23-D23-E23-F23 -> 0.19571528 | D21: 0.19611408 | E21: 0.18652029 | F21: 0.29740762 | G21: =+SUM(C21:F21) -> 0.87575727
B22: Industria | C22: 0.024108033 | D22: 0.025323022 | E22: 0.023403755 | F22: 0.027390289 | G22: =+SUM(C22:F22) -> 0.1002251
B23: Minería | C23: 0.0048643299 | D23: 0.0056477116 | E23: 0.0050998183 | F23: 0.0084057691 | G23: =+SUM(C23:F23) -> 0.024017629
B24: Mercado territorial
B25: Mercado Local | C25: 0.22263204 | D25: 0.2241423 | E25: 0.21163918 | F25: 0.30957319 | G25: =+SUM(C25:F25) -> 0.9679867
B26: Mercado Externo | C26: 0.0020556022 | D26: 0.0029425113 | E26: 0.00338469 | F26: 0.023630495 | G26: =+SUM(C26:F26) -> 0.032013298
B28: Proy 2024 | C28: 2500000
B29: Presupuesto de Ventas proyectado
B30: Trimestre | C30: 1T | D30: 2T | E30: 3T | F30: 4T | G30: TOTAL ANUAL
B31: Ingreso | C31: =+C32*$C$28 -> 561719.1 | D31: =+D32*$C$28 -> 567712.03 | E31: =+E32*$C$28 -> 537559.67 | F31: =+F32*$C$28 -> 833009.2 | G31: =+SUM(C31:F31) -> 2500000
B32: Participación total | C32: 0.22468764 | D32: 0.22708481 | E32: 0.21502387 | F32: 0.33320368
B34: Presupuesto de Ventas proyectado segmentado
B35: Trimestre | C35: 1T | D35: 2T | E35: 3T | F35: 4T | G35: TOTAL ANUAL
B36: Sector de mercado
B37: Construcción Civil | C37: =+C47*$C$28 -> 489288.19 | D37: =+D47*$C$28 -> 490285.19 | E37: =+E47*$C$28 -> 466300.74 | F37: =+F47*$C$28 -> 743519.06 | G37: =+SUM(C37:F37) -> 2189393.2
B38: Industria | C38: =+C48*$C$28 -> 60270.083 | D38: =+D48*$C$28 -> 63307.555 | E38: =+E48*$C$28 -> 58509.388 | F38: =+F48*$C$28 -> 68475.723 | G38: =+SUM(C38:F38) -> 250562.75
B39: Minería | C39: =+C49*$C$28 -> 12160.825 | D39: =+D49*$C$28 -> 14119.279 | E39: =+E49*$C$28 -> 12749.546 | F39: =+F49*$C$28 -> 21014.423 | G39: =+SUM(C39:F39) -> 60044.072
B40: Total | C40: =+C37+C38+C39 -> 561719.1 | D40: =+D37+D38+D39 -> 567712.03 | E40: =+E37+E38+E39 -> 537559.67 | F40: =+F37+F38+F39 -> 833009.2 | G40: =+G37+G38+G39 -> 2500000
B41: Mercado territorial
B42: Mercado Local | C42: =+C51*$C$28 -> 556580.1 | D42: =+D51*$C$28 -> 560355.75 | E42: =+E51*$C$28 -> 529097.94 | F42: =+F51*$C$28 -> 773932.97 | G42: =+SUM(C42:F42) -> 2419966.8
B43: Mercado Externo | C43: =+C52*$C$28 -> 5139.0056 | D43: =+D52*$C$28 -> 7356.2783 | E43: =+E52*$C$28 -> 8461.7249 | F43: =+F52*$C$28 -> 59076.237 | G43: =+SUM(C43:F43) -> 80033.245
B44: Total | C44: =+C42+C43 -> 561719.1 | D44: =+D42+D43 -> 567712.03 | E44: =+E42+E43 -> 537559.67 | F44: =+F42+F43 -> 833009.2 | G44: =+G42+G43 -> 2500000
B45: Participación
B46: Sector de mercado
B47: Construcción Civil | C47: 0.19571528 | D47: 0.19611408 | E47: 0.18652029 | F47: 0.29740762
B48: Industria | C48: 0.024108033 | D48: 0.025323022 | E48: 0.023403755 | F48: 0.027390289
B49: Minería | C49: 0.0048643299 | D49: 0.0056477116 | E49: 0.0050998183 | F49: 0.0084057691
B50: Mercado territorial
B51: Mercado Local | C51: 0.22263204 | D51: 0.2241423 | E51: 0.21163918 | F51: 0.30957319
B52: Mercado Externo | C52: 0.0020556022 | D52: 0.0029425113 | E52: 0.00338469 | F52: 0.023630495
B54: Ingresos al contado y crédito históricos
B55: Trimestre | C55: 1T | D55: 2T | E55: 3T | F55: 4T | G55: TOTAL ANUAL
B56: Ventas al contado | C56: 397808 | D56: 475015 | E56: 459640 | F56: 387070 | G56: =+SUM(C56:F56) -> 1719533
B57: Ventas al crédito (CXC) | C57: =+C58-C56 -> 138025.96 | D57: =+D58-D56 -> 66535.721 | E57: =+E58-E56 -> 53147.845 | F57: =+F58-F56 -> 407552.47 | G57: =+SUM(C57:F57) -> 665262
B58: Ingresos totales | C58: =+C6 -> 535833.96 | D58: =+D6 -> 541550.72 | E58: =+E6 -> 512787.84 | F58: =+F6 -> 794622.47 | G58: =+SUM(C58:F58) -> 2384795
B59: Part. Vent. Contado | C59: =+C56/C$58 -> 0.74240908 | D59: =+D56/D$58 -> 0.87713852 | E59: =+E56/E$58 -> 0.8963551 | F59: =+F56/F$58 -> 0.48711182 | G59: =+G56/G$58 -> 0.72104017
B60: Part. Vent. Crédito | C60: =+C57/C$58 -> 0.25759092 | D60: =+D57/D$58 -> 0.12286148 | E60: =+E57/E$58 -> 0.1036449 | F60: =+F57/F$58 -> 0.51288818 | G60: =+G57/G$58 -> 0.27895983
B62: Ingresos al contado y crédito proyectado al 2024
B63: Trimestre | C63: 1T | D63: 2T | E63: 3T | F63: 4T | G63: TOTAL ANUAL
B64: Ventas al contado | C64: 450172.8 | D64: 537541.62 | E64: 520147.32 | F64: 438017.58 | G64: =SUM(C64:F64) -> 1945879.3
B65: Ventas al crédito (CXC) | C65: =+C66-C64 -> 111546.3 | D65: =+D66-D64 -> 30170.406 | E65: =+E66-E64 -> 17412.35 | F65: =+F66-F64 -> 394991.62 | G65: =SUM(C65:F65) -> 554120.68
B66: Ingresos totales | C66: =+C31 -> 561719.1 | D66: =+D31 -> 567712.03 | E66: =+E31 -> 537559.67 | F66: =+F31 -> 833009.2 | G66: =SUM(C66:F66) -> 2500000
B67: Part. Vent. Contado | C67: =+C64/C$66 -> 0.80141978 | D67: =+D64/D$66 -> 0.94685614 | E67: =+E64/E$66 -> 0.96760853 | F67: =+F64/F$66 -> 0.52582562 | G67: =+G64/G$66 -> 0.77835173
B68: Part. Vent. Crédito | C68: =+C65/C$66 -> 0.19858022 | D68: =+D65/D$66 -> 0.053143856 | E68: =+E65/E$66 -> 0.032391473 | F68: =+F65/F$66 -> 0.47417438 | G68: =+G65/G$66 -> 0.22164827
B71: Producción anual histórica
B72: Trimestre | C72: 1T | D72: 2T | E72: 3T | F72: 4T | G72: TOTAL ANUAL
B73: TM producidas | C73: =+INT($G$73*C32) -> 125000 | D73: =+INT($G$73*D32) -> 126333 | E73: =+INT($G$73*E32) -> 119623 | F73: =+INT($G$73*F32) -> 185370 | G73: 556328
B75: Producción anual proyectada
B76: g = tasa de crecimiento industrial | D76: 0.05
B78: Trimestre | C78: 1T | D78: 2T | E78: 3T | F78: 4T | G78: TOTAL ANUAL
B79: TM producidas | C79: =+INT(C73*(1+$D$76)) -> 131250 | D79: =+INT(D73*(1+$D$76)) -> 132649 | E79: =+INT(E73*(1+$D$76)) -> 125604 | F79: =+INT(F73*(1+$D$76)) -> 194638 | G79: =+SUM(C79:F79) -> 584141

Sheet Presupuesto Ventas y Producción
B1: Presupueto de Venta y Producción
B2: 1) Presupuesto de Ventas
B3: Se elabora el presupuesto de Ventas y se presentan las políticas Comerciales de la empresas y sus resultados parciales y totales. (Para un mejor análisis, está expresado en soles s/)
B5: Rubros | C5: Unidades | D5: Pu | E5: Q | G5: Pu | H5: Q | J5: Pu | K5: Q | M5: Pu | N5: Q | P5: Total Anual
B6: Ventas al contado | C6: TM | D6: 4200 | E6: 97440 | F6: =+D6*E6 -> 409248000 | G6: 4260 | H6: 116351 | I6: =+G6*H6 -> 495655260 | J6: 4200 | K6: 112586 | L6: =+J6*K6 -> 472861200 | M6: 4200 | N6: 94809 | O6: =+M6*N6 -> 398197800 | P6: =+F6+I6+L6+O6 -> 1775962260
B7: Ventas al crédito | C7: TM | D7: 4620 | E7: 53500 | F7: =+D7*E7 -> 247170000 | G7: 4620 | H7: 36200 | I7: =+G7*H7 -> 167244000 | J7: 4620 | K7: 31800 | L7: =+J7*K7 -> 146916000 | M7: 4620 | N7: 41200 | O7: =+M7*N7 -> 190344000 | P7: =+F7+I7+L7+O7 -> 751674000
B8: Total | C8: TM | D8: =+F8/E8 -> 4348.8671 | E8: =+SUM(E6:E7) -> 150940 | F8: =+SUM(F6:F7) -> 656418000 | G8: =+I8/H8 -> 4345.4272 | H8: =+SUM(H6:H7) -> 152551 | I8: =+SUM(I6:I7) -> 662899260 | J8: =+L8/K8 -> 4292.502 | K8: =+SUM(K6:K7) -> 144386 | L8: =+SUM(L6:L7) -> 619777200 | M8: =+O8/N8 -> 4327.2269 | N8: =+SUM(N6:N7) -> 136009 | O8: =+SUM(O6:O7) -> 588541800 | P8: =+F8+I8+L8+O8 -> 2527636260
B10: 1.a) Política Comercial
B11: 1.b) Resultados económicos
B12: La empresa presenta un nivel de ingresos por ventas de de s/ 2.63 billones proyectados
B13: El precio de venta al contado promedio con proyección de datos histórica es de s/ 4 279.86 por TM; sin embargo, para un mejor mejor análisis, es redondeado a s/ 4 200.
B14: Los resultados parciales muestra una caída de precio en los trimestre siguientes debido a la estabilidad del precio del cobre. Por ello, en el presupueto de ventas, se ve afectado principalmente por el Efecto Precio, seguido del Efecto Volumen.
B15: Los precios promedios de ventas totales son de s/ 4 471, s/ 4 535, s/ 4 527 y s/ 4493 para los periodos 1T, 2T, 3T y 4T, respectivamente
B17: 2) Presupuesto de Producción
B18: Se elabora el presupuesto de Producción a través de la Política de costos e inventarios. Ambas se detallan al finalizar el cuadro (Para un mejor análisis, está expresado en soles s/)
B20: Rubros | C20: Unidades | D20: Pu | E20: Q | G20: Pu | H20: Q | J20: Pu | K20: Q | M20: Pu | N20: Q | P20: Total Anual
B21: MOD | C21: HH | D21: 12 | E21: =5*E28 -> 677360.5 | F21: =+D21*E21 -> 8128326 | G21: 12 | H21: =5*H28 -> 758896 | I21: =+G21*H21 -> 9106752 | J21: 12 | K21: =5*K28 -> 717935.5 | L21: =+J21*K21 -> 8615226 | M21: 12 | N21: =5*N28 -> 765238 | O21: =+M21*N21 -> 9182856 | P21: =+F21+I21+L21+O21 -> 35033160
B22: MTD | C22: TM | D22: =860*1.5 -> 1290 | E22: =1.5*E28 -> 203208.15 | F22: =+D22*E22 -> 2.6213851e+08 | G22: =840*1.5 -> 1260 | H22: =1.5*H28 -> 227668.8 | I22: =+G22*H22 -> 286862688 | J22: =820*1.5 -> 1230 | K22: =1.5*K28 -> 215380.65 | L22: =+J22*K22 -> 2.649182e+08 | M22: =1.5*830 -> 1245 | N22: =1.5*N28 -> 229571.4 | O22: =+M22*N22 -> 285816393 | P22: =+F22+I22+L22+O22 -> 1099735794
B23: CIF | C23: S/ | F23: =+(F21+F22)*30/70 -> 1.1582865e+08 | I23: =+(I21+I22)*30/70 -> 1.2684405e+08 | L23: =+(L21+L22)*30/70 -> 1.1722861e+08 | O23: =+(O21+O22)*30/70 -> 1.2642825e+08 | P23: =+F23+I23+L23+O23 -> 4.8632955e+08
B24: Costo totales | D24: =+F24/E24 -> 2850 | E24: =+E28 -> 135472.1 | F24: =+SUM(F21:F23) -> 386095485 | G24: =+I24/H24 -> 2785.7143 | H24: =+H28 -> 151779.2 | I24: =+SUM(I21:I23) -> 4.2281349e+08 | J24: =+L24/K24 -> 2721.4286 | K24: =+K28 -> 143587.1 | L24: =+SUM(L21:L23) -> 3.9076204e+08 | M24: =+O24/N24 -> 2753.5714 | N24: =+N28 -> 153047.6 | O24: =+SUM(O21:O23) -> 4.214275e+08 | P24: =+F24+I24+L24+O24 -> 1.6210985e+09
B25: IIPT | C25: TM | E25: 30000 | H25: =+E27 -> 14532.1 | K25: =+H27 -> 13760.3 | N25: =+K27 -> 12961.4
B26: Requerimiento de ventas | C26: TM | E26: =+E8 -> 150940 | H26: =+H8 -> 152551 | K26: =+K8 -> 144386 | N26: =+N8 -> 136009
B27: IFPT | C27: TM | E27: =+D43*0.1 -> 14532.1 | H27: =+E43*0.1 -> 13760.3 | K27: =+F43*0.1 -> 12961.4 | N27: 30000
B28: Unidades a producir | C28: TM | E28: =+E27+E26-E25 -> 135472.1 | H28: =+H27+H26-H25 -> 151779.2 | K28: =+K27+K26-K25 -> 143587.1 | N28: =+N27+N26-N25 -> 153047.6 | P28: =+E28+H28+K28+N28 -> 583886
B30: 2.a) Política de Costos
B31: Los costos para Mano de Obra Directa (MOD) se proyecta en s/12 para todo el año
B32: Los costos para Matariales Indirectos de Fabricación son variables respecto a la variación del precio de cobre; s/1720 para el 1T; s/ 1680, para 2T; s/ 1640, para 3T y s/ 1660 para el último trimestre
B33: Los costos CIF son totales, de manera trimestral, y tienen un 30% participación del total de Costos Totales en promedio.
B34: Los requerimientos para la realización de productos es de 5 horas hombre por cada TM producida y 1.5 TM de insumos en general por cada TM de acero producido; ambos factores permanecen constante en los 4 trimestre.
B35: 2.b) Políticas de Inventario
B36: La política de Inventario es mantener 10% de la cantidades proyectadas para cada periodo al termino de este
B37: Así como, iniciar cada año con 30 000 TM Estas proyecciones se realizan con el nivel de producción trimestral del año 2023 y con una tasa de crecimiento del 5%.
B38: Así mismo, se detalla el promedio histórico de la participación de las cuentas de Costo de Ventas
B39: Participación | C39: MOD | D39: 0.1 | F39: MTD | G39: 0.6 | H39: CIF | J39: 0.3
B40: Así mismo, se detalla el nivel histórico de producción a partir de información histórica del año 2023.
B41: Producción anual histórica
B42: Trimestre | C42: 1T | D42: 2T | E42: 3T | F42: 4T | G42: TOTAL ANUAL
B43: TM producidas | C43: 143787 | D43: 145321 | E43: 137603 | F43: 129614 | G43: 556328
B44: Así mismo, se detalla el nivel proyectado de producción a partir de información histórica y de la tasa de crecimiento del sector siderúrgico, industrial y minero.
B45: Producción anual proyectada
B46: g = tasa de crecimiento industrial | D46: 0.05
B47: Trimestre | C47: 1T | D47: 2T | E47: 3T | F47: 4T | G47: TOTAL ANUAL
B48: TM producidas | C48: 131250 | D48: 132649 | E48: 125604 | F48: 194638 | G48: =+SUM(C48:F48) -> 584141
B50: 2.c) Resultados económicos
B51: Se evidencia un nivel de costo total anual de s/ 2.145 billones proyectado.
B52: Así mismo, se proyecta un nivel total dede 584 136 TM producidas para el año 2024, siendo - 4 TM de las proyectadas con el crecimiento de la industria.
B53: La empresa cubre con su Inventario Inicial de Productos Terminados (IIPT) e Inventrio Final de Productos Terminados (IFPT) teniendo capital de trabajo no ocioso, acorde a la política interna.
B54: Se evidencia un decrecimiento total en los costos productivos de la empresa; de s/ 3 771, s/ 3 686, s/ 3 600 y s/ 3 643 para 1T, 2T, 3T y 4T, respectivamente.
B55: Este decrecimiento total en los costos es impulsado por la reducción de los costos de insumos en Materiales Directos (MD) bajo el supuesto de la estabilidad de precios del acero.

Sheet Presupuesto de Gastos Generales
B2: Presupuesto de Gastos Generales
B3: Se presenta el Presupuesto de Gastos Generales por cada una de sus cuentas para un mayor análisis.
B4: 1) Gastos de Ventas
B5: Se realiza el presupuestos de Gastos de Ventas con los datos de las cuentas del año 2023. Se asume que no existe variación de los gastos.
B7: Trimestre | C7: 1T | D7: 2T | E7: 3T | F7: 4T | G7: Total anual
B8: Gastos de personal | C8: 2341 | D8: =2341*7/6 -> 2731.1667 | E8: 2341 | F8: =2341*7/6 -> 2731.1667 | G8: =+SUM(C8:F8) -> 10144.333
B9: Servicios de publicidad y Marketing | C9: 1147 | D9: 1147 | E9: 1147 | F9: 1147 | G9: =+SUM(C9:F9) -> 4588
B10: Servicios prestados por terceros | C10: 1299 | D10: 1299 | E10: 1299 | F10: 1299 | G10: =+SUM(C10:F10) -> 5196
B11: Depreciación | C11: 195 | D11: 195 | E11: 195 | F11: 195 | G11: =+SUM(C11:F11) -> 780
B12: Estimación de recupero para deterioro de cuentas por cobrar | C12: 70 | D12: 70 | E12: 70 | F12: 70 | G12: =+SUM(C12:F12) -> 280
B13: Total trimestral | C13: =+SUM(C8:C12) -> 5052 | D13: =+SUM(D8:D12) -> 5442.1667 | E13: =+SUM(E8:E12) -> 5052 | F13: =+SUM(F8:F12) -> 5442.1667 | G13: =+SUM(C13:F13) -> 20988.333
B15: 2) Gastos Administrativos
B16: Se realiza el presupuestos de Gastos Administrativos con los datos de las cuentas del año 2023. Se asume que no existe variación de los gastos.
B18: Trimestre | C18: 1T | D18: 2T | E18: 3T | F18: 4T | G18: Total anual
B19: Gasto de personal | C19: 5466 | D19: =5466*7/6 -> 6377 | E19: 5466 | F19: =5466*7/6 -> 6377 | G19: =+SUM(C19:F19) -> 23686
B20: Servicios prestados por terceros | C20: 4299 | D20: 4299 | E20: 4299 | F20: 4299 | G20: =+SUM(C20:F20) -> 17196
B21: Servicios de asesoria | C21: 675 | D21: 675 | E21: 675 | F21: 675 | G21: =+SUM(C21:F21) -> 2700
B22: Depreciación | C22: 438 | D22: 438 | E22: 438 | F22: 438 | G22: =+SUM(C22:F22) -> 1752
B23: Amortización | C23: 14 | D23: 14 | E23: 14 | F23: 14 | G23: =+SUM(C23:F23) -> 56
B24: Servicio de suscripción de medios de información | C24: 222 | D24: 222 | E24: 222 | F24: 222 | G24: =+SUM(C24:F24) -> 888
B25: Gastos de viaje | C25: 128 | D25: 128 | E25: 128 | F25: 128 | G25: =+SUM(C25:F25) -> 512
B26: Servicios de v igilancia | C26: 104 | D26: 104 | E26: 104 | F26: 104 | G26: =+SUM(C26:F26) -> 416
B27: Impuestos a las transacciones financieras | C27: 100 | D27: 100 | E27: 100 | F27: 100 | G27: =+SUM(C27:F27) -> 400
B28: Tributos | C28: 28 | D28: 28 | E28: 28 | F28: 28 | G28: =+SUM(C28:F28) -> 112
B29: Otros | C29: 249 | D29: 249 | E29: 249 | F29: 249 | G29: =+SUM(C29:F29) -> 996
B30: Total trimestral | C30: =+SUM(C19:C29) -> 11723 | D30: =+SUM(D19:D29) -> 12634 | E30: =+SUM(E19:E29) -> 11723 | F30: =+SUM(F19:F29) -> 12634 | G30: =+SUM(C30:F30) -> 48714
B32: 3) Otros Ingresos
B33: Se realiza el presupuestos de Otros Ingresos con los datos de las cuentas del año 2023. Se asume que no existe variación de los gastos.
B35: Trimestre | C35: 1T | D35: 2T | E35: 3T | F35: 4T | G35: Total anual
B36: Total trimestral de Otros Ingresos | C36: 1551 | D36: 1551 | E36: 1551 | F36: 1551 | G36: =+SUM(C36:F36) -> 6204
B37: Nota: Comprende la recuperación de activos contables como estimaciones de ejercicios anteriores, chatarra de activo fijo, siniestros, de cuentas por cobrar provisionales y contratos leasing
B40: 4) Otros gastos
B41: Se realiza el presupuestos de Otros Gastos con los datos de las cuentas del año 2023. Se asume que no existe variación de los gastos.
B43: Trimestre | C43: 1T | D43: 2T | E43: 3T | F43: 4T | G43: Total anual
B44: Total trimestral de Otros gastos | C44: 1010 | D44: 1010 | E44: 1010 | F44: 1010 | G44: =+SUM(C44:F44) -> 4040
B45: Nota: Comprende sanciones administrativas fiscales, gastos de años anteriores y costos de enajenación de propiedad, planta y equipo.
B48: 5) Ingresos Financieros
B49: Se realiza el presupuestos de Ingresos Financiera con los datos de las cuentas del año 2023. Se asume que no existe variación de los gastos.
B51: Trimestre | C51: 1T | D51: 2T | E51: 3T | F51: 4T | G51: Total anual
B52: Intereses por depósitos a plazos | C52: 988 | D52: 988 | E52: 988 | F52: 988 | G52: =+SUM(C52:F52) -> 3952
B53: Interes por cuentas por cobrar comerciales | C53: 35 | D53: 35 | E53: 35 | F53: 35 | G53: =+SUM(C53:F53) -> 140
B54: Intereses por otras cuentas por cobrar | C54: 56 | D54: 56 | E54: 56 | F54: 56 | G54: =+SUM(C54:F54) -> 224
B55: Total trimestral | C55: =+SUM(C40:C54) -> 2089 | D55: =+SUM(D40:D54) -> 2089 | E55: =+SUM(E40:E54) -> 2089 | F55: =+SUM(F40:F54) -> 2089 | G55: =+SUM(C55:F55) -> 8356
B57: 6) Gastos Financieros
B58: Se realiza el presupuestos de Gastos Financieros con los datos de las cuentas del año 2023. Se asume que no existe variación de los gastos.
B60: Trimestre | C60: 1T | D60: 2T | E60: 3T | F60: 4T | G60: Total anual
B61: Intereses por arrendamiento operativo | C61: 139 | D61: 139 | E61: 139 | F61: 139 | G61: =+SUM(C61:F61) -> 556
B62: Intereses por préstamos bancarios | C62: 5474 | D62: 5474 | E62: 5474 | F62: 5474 | G62: =+SUM(C62:F62) -> 21896
B63: Otros menores | C63: 937 | D63: 937 | E63: 937 | F63: 937 | G63: =+SUM(C63:F63) -> 3748
B64: Total trimestral | C64: =+SUM(C51:C63) -> 9718 | D64: =+SUM(D51:D63) -> 9718 | E64: =+SUM(E51:E63) -> 9718 | F64: =+SUM(F51:F63) -> 9718 | G64: =+SUM(C64:F64) -> 38872

Sheet EERR y Cash Flow proyectad
B2: 1) Estado de Resultados proyectado para el año 2024
B3: Se presenta el EERR proyectado con los valores proyectado en los análisis anteriores.
B4: Trimestre | C4: 1T | D4: 2T | E4: 3T | F4: 4T | G4: Anual
B5: Ingresos por Ventas | C5: =+'Presupuesto Ventas y Producción'!F8/1000 -> 656418 | D5: =+'Presupuesto Ventas y Producción'!I8/1000 -> 662899.26 | E5: =+'Presupuesto Ventas y Producción'!L8/1000 -> 619777.2 | F5: =+'Presupuesto Ventas y Producción'!O8/1000 -> 588541.8 | G5: =+SUM(C5:F5) -> 2527636.3
B6: Costos de Ventas | C6: =+'Presupuesto Ventas y Producción'!F24/1000 -> 386095.48 | D6: =+'Presupuesto Ventas y Producción'!I24/1000 -> 422813.49 | E6: =+'Presupuesto Ventas y Producción'!L24/1000 -> 390762.04 | F6: =+'Presupuesto Ventas y Producción'!O24/1000 -> 421427.5 | G6: =+SUM(C6:F6) -> 1621098.5
B7: Utilidad Bruta | C7: =+C5-C6 -> 270322.52 | D7: =+D5-D6 -> 240085.77 | E7: =+E5-E6 -> 229015.16 | F7: =+F5-F6 -> 167114.3 | G7: =+SUM(C7:F7) -> 906537.75
B8: Gastos de Ventas | C8: =+'Presupuesto de Gastos Generales'!C13 -> 5052 | D8: =+'Presupuesto de Gastos Generales'!D13 -> 5442.1667 | E8: =+'Presupuesto de Gastos Generales'!E13 -> 5052 | F8: =+'Presupuesto de Gastos Generales'!F13 -> 5442.1667 | G8: =+SUM(C8:F8) -> 20988.333
B9: Gastos Administrativos | C9: {=+'Presupuesto de Gastos Generales'!C30:F30} -> 11723 | D9: 12634 | E9: 11723 | F9: 12634 | G9: =+SUM(C9:F9) -> 48714
B10: Otros Ingresos | C10: {=+'Presupuesto de Gastos Generales'!C36:F36} -> 1551 | D10: 1551 | E10: 1551 | F10: 1551 | G10: =+SUM(C10:F10) -> 6204
B11: Otros Gastos | C11: {=+'Presupuesto de Gastos Generales'!C44:F44} -> 1010 | D11: 1010 | E11: 1010 | F11: 1010 | G11: =+SUM(C11:F11) -> 4040
B12: Utilidad Operativa | C12: =+C7-C8-C9-+C10-C11 -> 250986.52 | D12: =+D7-D8-D9-+D10-D11 -> 219448.61 | E12: =+E7-E8-E9-+E10-E11 -> 209679.16 | F12: =+F7-F8-F9-+F10-F11 -> 146477.13 | G12: =+SUM(C12:F12) -> 826591.42
B13: Otros Ingresos Financieros | C13: {=+'Presupuesto de Gastos Generales'!C55:F55} -> 2089 | D13: 2089 | E13: 2089 | F13: 2089 | G13: =+SUM(C13:F13) -> 8356
B14: Otros Gastos Financieros | C14: {=+'Presupuesto de Gastos Generales'!C64:F64} -> 9718 | D14: 9718 | E14: 9718 | F14: 9718 | G14: =+SUM(C14:F14) -> 38872
B15: Utilidad ante de impuestos | C15: =+C12+C13-C14 -> 243357.52 | D15: =+D12+D13-D14 -> 211819.61 | E15: =+E12+E13-E14 -> 202050.16 | F15: =+F12+F13-F14 -> 138848.13 | G15: =+SUM(C15:F15) -> 796075.42
B16: Impuestos | C16: =+C15*(0.295) -> 71790.467 | D16: =+D15*(0.295) -> 62486.784 | E16: =+E15*(0.295) -> 59604.798 | F16: =+F15*(0.295) -> 40960.2 | G16: =+SUM(C16:F16) -> 234842.25
B17: Utilidad Neta | C17: =+C15-C16 -> 171567.05 | D17: =+D15-D16 -> 149332.82 | E17: =+E15-E16 -> 142445.37 | F17: =+F15-F16 -> 97887.935 | G17: =+SUM(C17:F17) -> 561233.17
B18: Nota: Estado de Resultado expresado en miles de s/
B20: 2) Flow Cash proyectado (sin financiamiento ni inversión)
B21: El Flow Cash se proyecta con los valores de la empresa
B22: Trimestre | C22: 1T | D22: 2T | E22: 3T | F22: 4T | G22: Anual
B23: Ingresos Operativos | C23: =+C5 -> 656418 | D23: =+D5 -> 662899.26 | E23: =+E5 -> 619777.2 | F23: =+F5 -> 588541.8 | G23: =+G5 -> 2527636.3
B24: Egresos Operativos | C24: =+C25+C26+C27-C28+C29-C30+C31 -> 409958.48 | D24: =+D25+D26+D27-D28+D29-D30+D31 -> 447977.65 | E24: =+E25+E26+E27-E28+E29-E30+E31 -> 414625.04 | F24: =+F25+F26+F27-F28+F29-F30+F31 -> 446591.67 | G24: =+G25+G26+G27-G28+G29-G30+G31 -> 1719152.8
B25: Costos de Venta | C25: =+C6 -> 386095.48 | D25: =+D6 -> 422813.49 | E25: =+E6 -> 390762.04 | F25: =+F6 -> 421427.5 | G25: =+G6 -> 1621098.5
B26: Gastos de ventas | C26: =+C8 -> 5052 | D26: =+D8 -> 5442.1667 | E26: =+E8 -> 5052 | F26: =+F8 -> 5442.1667 | G26: =+G8 -> 20988.333
B27: Gastos Administrativos | C27: =+C9 -> 11723 | D27: =+D9 -> 12634 | E27: =+E9 -> 11723 | F27: =+F9 -> 12634 | G27: =+G9 -> 48714
B28: Otros Ingresos | C28: =+C10 -> 1551 | D28: =+D10 -> 1551 | E28: =+E10 -> 1551 | F28: =+F10 -> 1551 | G28: =+G10 -> 6204
B29: Otros Gastos | C29: =+C11 -> 1010 | D29: =+D11 -> 1010 | E29: =+E11 -> 1010 | F29: =+F11 -> 1010 | G29: =+G11 -> 4040
B30: Ingresos Financieros | C30: =+C13 -> 2089 | D30: =+D13 -> 2089 | E30: =+E13 -> 2089 | F30: =+F13 -> 2089 | G30: =+G13 -> 8356
B31: Gastos Financieros | C31: =+C14 -> 9718 | D31: =+D14 -> 9718 | E31: =+E14 -> 9718 | F31: =+F14 -> 9718 | G31: =+G14 -> 38872
B32: Ingresos Netos Operativos | C32: =+C23-C24 -> 246459.52 | D32: =+D23-D24 -> 214921.61 | E32: =+E23-E24 -> 205152.16 | F32: =+F23-F24 -> 141950.13 | G32: =+G23-G24 -> 808483.42
B33: Saldo Inicial | C33: =87583 -> 87583 | D33: =+C34 -> 334042.52 | E33: =+D34 -> 548964.12 | F33: =+E34 -> 754116.29 | G33: =+C33 -> 87583
B34: Saldo Final | C34: =+C32+C33 -> 334042.52 | D34: =+D32+D33 -> 548964.12 | E34: =+E32+E33 -> 754116.29 | F34: =+F32+F33 -> 896066.42 | G34: =+F34 -> 896066.42
B36: 3) Flow Cash proyectado con financiamiento e inversión
B37: A fin de cumplir con el análisis del Capital de T rabajo, se presenta el Flow Cash proyectado con los valores respaldados por cada presupuesto individual.
B39: =B22 -> Trimestre | C39: =C22 -> 1T | D39: =D22 -> 2T | E39: =E22 -> 3T | F39: =F22 -> 4T | G39: =G22 -> Anual
B40: =B23 -> Ingresos Operativos | C40: =C23 -> 656418 | D40: =D23 -> 662899.26 | E40: =E23 -> 619777.2 | F40: =F23 -> 588541.8 | G40: =G23 -> 2527636.3
B41: Financiamiento | C41: 50000 | E41: 60000 | G41: =+SUM(C41:F41) -> 110000
B42: =B24 -> Egresos Operativos | C42: =+C43+C44+C45+C46+C47+C48+C49+C51 -> 417238.48 | D42: =+D43+D44+D45+D46+D47+D48+D49+D51 -> 455257.65 | E42: =+E43+E44+E45+E46+E47+E48+E49+E51 -> 368405.04 | F42: =+F43+F44+F45+F46+F47+F48+F49+F51 -> 453871.67 | G42: =+SUM(C42:F42) -> 1694772.8
B43: =B25 -> Costos de Venta | C43: =C25 -> 386095.48 | D43: =D25 -> 422813.49 | E43: =E25 -> 390762.04 | F43: =F25 -> 421427.5 | G43: =+SUM(C43:F43) -> 1621098.5
B44: =B26 -> Gastos de ventas | C44: =C26 -> 5052 | D44: =D26 -> 5442.1667 | E44: =E26 -> 5052 | F44: =F26 -> 5442.1667 | G44: =+SUM(C44:F44) -> 20988.333
B45: =B27 -> Gastos Administrativos | C45: =C27 -> 11723 | D45: =D27 -> 12634 | E45: =E27 -> 11723 | F45: =F27 -> 12634 | G45: =+SUM(C45:F45) -> 48714
B46: =B28 -> Otros Ingresos | C46: =C28 -> 1551 | D46: =D28 -> 1551 | E46: =E28 -> 1551 | F46: =F28 -> 1551 | G46: =+SUM(C46:F46) -> 6204
B47: =B29 -> Otros Gastos | C47: =C29 -> 1010 | D47: =D29 -> 1010 | E47: =E29 -> 1010 | F47: =F29 -> 1010 | G47: =+SUM(C47:F47) -> 4040
B48: =B30 -> Ingresos Financieros | C48: =C30 -> 2089 | D48: =D30 -> 2089 | E48: =E30 -> 2089 | F48: =F30 -> 2089 | G48: =+SUM(C48:F48) -> 8356
B49: =B31 -> Gastos Financieros | C49: =C31 -> 9718 | D49: =D31 -> 9718 | E49: =E31 -> 9718 | F49: =F31 -> 9718 | G49: =+SUM(C49:F49) -> 38872
B50: =B32 -> Ingresos Netos Operativos | C50: =+C40+C41-C42 -> 289179.52 | D50: =+D40+D41-D42 -> 207641.61 | E50: =+E40+E41-E42 -> 311372.16 | F50: =+F40+F41-F42 -> 134670.13 | G50: =+G40+G41-G42 -> 942863.42
B51: Pagos de deudas de CP nuevas | E51: =+-C41*(1+(0.14/2)) -> -53500 | G51: =+SUM(C51:F51) -> -53500
B52: Actividades de Financiamiento | C52: =+C51 -> 0 | D52: =+D51 -> 0 | E52: =+E51 -> -53500 | F52: =+F51 -> 0 | G52: =+SUM(C52:F52) -> -53500
B53: Inversión | E53: -8985.8729 | F53: -134939.71 | G53: =+SUM(C53:F53) -> -143925.58
B54: Rentabilidad de Inversión | F54: =+-E53*0.03 -> 269.57619 | G54: =+SUM(C54:F54) -> 269.57619
B55: Actividades de Inversión | C55: =+C53+C54 -> 0 | D55: =+D53+D54 -> 0 | E55: =+E53+E54 -> -8985.8729 | F55: =+F53+F54 -> -134670.13 | G55: =+SUM(C55:F55) -> -143656.01
B56: Flujo de caja | C56: =+C50+C52+C55 -> 289179.52 | D56: =+D50+D52+D55 -> 207641.61 | E56: =+E50+E52+E55 -> 248886.29 | F56: =+F50+F52+F55 -> 0.00094807072 | G56: =+SUM(C56:F56) -> 745707.41
B57: =B33 -> Saldo Inicial | C57: =C33 -> 87583 | D57: =+C58 -> 376762.52 | E57: =+D58 -> 584404.12 | F57: =+E58 -> 833290.41 | G57: =+C57 -> 87583
B58: =B34 -> Saldo Final | C58: =+C57+C56 -> 376762.52 | D58: =+D57+D56 -> 584404.12 | E58: =+E56+E57 -> 833290.41 | F58: =+F57+F56 -> 833290.41 | G58: =+F58 -> 833290.41

Sheet Capital de Trabajo
B1: Capital de trabajo
B2: Administración del Capital de Trabajo
B4: Capital de Trabajo Bruto
B5: =+'Balance Proforma'!C19+'Balance Proforma'!C20+'Balance Proforma'!C21 -> 1057831
B8: Capital de Trabajo Neto
B9: =+'Balance Proforma'!C19+'Balance Proforma'!C20+'Balance Proforma'!C21-'Balance Proforma'!F20-'Balance Proforma'!F21-'Balance Proforma'!F19 -> 3258
B26: 1) Cash management
B27: Ciclo de Caja
B29: Rotación de Inventarios
B30: =365/(-EERR!M3/ESF!N7) -> 96.172763
B33: Rotación de cuentas por cobrar
B34: =365/(EERR!M2/ESF!N3) -> 52.617006
B37: Rotación de Cuentas por Cobrar
B38: =365/(EERR!M2/ESF!N24) -> 60.473136
B41: Ciclo de Caja
B42: =+B30+B34-B38 -> 88.316633
B45: Caja Mínima
B46: =((2670385-1960138)-(19318-49090)/('Capital de Trabajo'!B42/365)) -> 833290.41

Sheet Valuacion
B2: Dato | C2: Valor (s/ o TM)
B3: Ingresos Operativos | C3: 2527636.3
B4: Financiamiento | C4: 110000
B5: Egresos Operativos | C5: 1694772.8
B6: Costos de Venta | C6: 1621098.5
B7: Gastos de ventas | C7: 20988.333
B8: Gastos Administrativos | C8: 48714
B9: Otros Ingresos | C9: 6204
B10: Otros Gastos | C10: 4040
B11: Ingresos Financieros | C11: 8356
B12: Gastos Financieros | C12: 38872
B13: MOD | C13: 35033160
B14: MD | C14: 1099735794
B15: CIF | C15: 4.8632955e+08
B16: Cantidad producida | C16: =+'Presupuesto Ventas y Producción'!P28 -> 583886
B17: Precio de Venta unitario | C17: =+'Presupuesto Ventas y Producción'!P8/('Presupuesto Ventas y Producción'!N8+'Presupuesto Ventas y Producción'!K8+'Presupuesto Ventas y Producción'!H8+'Presupuesto Ventas y Producción'!E8) -> 4328.9893
B18: Costos de Venta unitario | C18: =+C6*1000/C16 -> 2776.3956
C20: Costo Fijo | D20: Costo Variable
B21: MOD | D21: =+C13 -> 35033160
B22: MD | D22: =+C14 -> 1099735794
B23: CIF | C23: =+C15 -> 4.8632955e+08
B24: =+B7 -> Gastos de ventas | C24: =+C7 -> 20988.333
B25: =+B8 -> Gastos Administrativos | C25: =+C8+C9-C10 -> 50878
B26: Gastos Financieros | C26: =+C12-C11 -> 30516
B27: Total parcial | C27: =+SUM(C21:C26) -> 4.8643193e+08 | D27: =+SUM(D21:D26) -> 1134768954
B28: Total | C28: =+C27+D27 -> 1.6212009e+09
B30: Resultados | C30: Valor
B31: Costo operativo | C31: =+(C28-C26)/C16 -> 2776.5187
B32: Costo financiero | C32: =+C26/C16 -> 0.052263627
B33: Punto de equilibrio | C33: =+C27/(C17-C18) -> 313302.78
B35: Cuenta | C35: Valo (Q real) | D35: Valor (Q equilibrio)
B36: Ingresos | C36: =+C17*C16 -> 2527636260 | D36: =+C17*C33 -> 1.3562844e+09
B37: Costos | C37: =+C27+C18*C16 -> 2.1075304e+09 | D37: =+C27+C18*C33 -> 1.3562844e+09
B38: Utilidad | C38: =+C36-C37 -> 4.2010582e+08 | D38: =+D36-D37 -> 0

Sheet TRI Y CAPM
B2: Tasa de Retorno de la Inversión
B3: Año | C3: 2012 | D3: 2013 | E3: 2014 | F3: 2015 | G3: 2016 | H3: 2017 | I3: 2018 | J3: 2019 | K3: 2020 | L3: 2021 | M3: 2022 | N3: 2023 | O3: 2024
B4: TRI | C4: =+EERR!B9/(ESF!B10+ESF!B18) -> -0.14746261 | D4: =+EERR!C9/(ESF!C10+ESF!C18) -> 0.063476949 | E4: =+EERR!D9/(ESF!D10+ESF!D18) -> -0.30710481 | F4: =+EERR!E9/(ESF!E10+ESF!E18) -> 0.039117582 | G4: =+EERR!F9/(ESF!F10+ESF!F18) -> 0.099680031 | H4: =+EERR!G9/(ESF!G10+ESF!G18) -> 0.11432288 | I4: =+EERR!H9/(ESF!H10+ESF!H18) -> 0.098468293 | J4: =+EERR!I9/(ESF!I10+ESF!I18) -> 0.073227201 | ... N4: =+EERR!M9/(ESF!M10+ESF!M18) -> 0.10660251 | O4: =+'EERR y Cash Flow proyectad'!G12/('Balance Proforma'!C24+'Balance Proforma'!C32) -> 0.29943519
B6: Esquema Du Pont
B7: Indicador | C7: Valor
B8: Utilidad Operativa | C8: =+'EERR y Cash Flow proyectad'!G12 -> 826591.42
B9: Activos operativos | C9: =+('Balance Proforma'!C24+'Balance Proforma'!C32) -> 2760502
B10: TRI | C10: =+C8/C9 -> 0.29943519
B13: Costo de Oportunidad del Capital
B14: Tasaa | C14: Valores (%)
B15: Tasa de deuda | C15: 0.08
B16: Tasa de Riesgo País | C16: 0.0167
B17: Tasa de inflación | C17: 0.032
B18: Costo de Oportunidad | C18: =+((1+C15)*(1+C16)*(1+C17))-1 -> 0.13317315
B19: WACC (2019) | C19: 0.1087

Sheet CONTROL PRESUPUESTAL
B4: Trimestre | C4: Presupuesto 1T24 | D4: Ejecutado 1T24 | E4: Variación | F4: Variación
B5: Ingresos por Ventas | C5: 656418 | D5: 556255 | E5: =+D5-C5 -> -100163 | F5: =1-(D5/C5) -> 0.15259027
B6: Costos de Ventas | C6: 386095.48 | D6: 465604 | E6: =+D6-C6 -> 79508.515 | F6: =1-(D6/C6) -> -0.20592967
B7: Utilidad Bruta | C7: 270322.52 | D7: =+D5-D6 -> 90651 | E7: =+D7-C7 -> -179671.52 | F7: =1-(D7/C7) -> 0.66465612
B8: Gastos de Ventas | C8: 5052 | D8: 4998 | E8: =+D8-C8 -> -54 | F8: =1-(D8/C8) -> 0.010688836
B9: Gastos Administrativos | C9: 11723 | D9: 10065 | E9: =+D9-C9 -> -1658 | F9: =1-(D9/C9) -> 0.14143137
B10: Otros Ingresos | C10: 1551 | D10: 5755 | E10: =+D10-C10 -> 4204 | F10: =1-(D10/C10) -> -2.7105093
B11: Otros Gastos | C11: 1010 | D11: 1553 | E11: =+D11-C11 -> 543 | F11: =1-(D11/C11) -> -0.53762376
B12: Utilidad Operativa | C12: 250986.52 | D12: =+D7-D8-D9-D11+D10 -> 79790 | E12: =+D12-C12 -> -171196.52 | F12: =1-(D12/C12) -> 0.68209447
B13: Otros Ingresos Financieros | C13: 2089 | D13: 939 | E13: =+D13-C13 -> -1150 | F13: =1-(D13/C13) -> 0.55050263
B14: Otros Gastos Financieros | C14: 9718 | D14: 6027 | E14: =+D14-C14 -> -3691 | F14: =1-(D14/C14) -> 0.37981066
B15: Utilidad ante de impuestos | C15: 243357.52 | D15: =+D12+D13-D14 -> 74702 | E15: =+D15-C15 -> -168655.52 | F15: =1-(D15/C15) -> 0.69303598
